aws_boto3/__init__.py
aws_boto3/common.py
aws_boto3/dynamodb.py
aws_boto3/ec2.py
aws_boto3/ecr.py
aws_boto3/kms.py
aws_boto3/lookup.py
aws_boto3/s3.py
aws_boto3/utils.py
aws_boto3/ecs/__init__.py
aws_boto3/ecs/utils.py
aws_boto3/iam/__init__.py
aws_boto3/iam/policies.py
aws_boto3/iam/roles.py
aws_boto3/lambdas/__init__.py
aws_boto3/lambdas/utils.py
salt_aws_boto3-0.1.10.dist-info/DESCRIPTION.rst
salt_aws_boto3-0.1.10.dist-info/METADATA
salt_aws_boto3-0.1.10.dist-info/RECORD
salt_aws_boto3-0.1.10.dist-info/WHEEL
salt_aws_boto3-0.1.10.dist-info/metadata.json
salt_aws_boto3-0.1.10.dist-info/top_level.txt
tests/__init__.py
