Metadata-Version: 2.0
Name: salt-aws-boto3
Version: 0.1.10
Summary: Use boto3 for AWS orchestration with Salt.
Home-page: https://github.com/intuitivetechnologygroup/salt-aws-boto3
Author: meganlkm
Author-email: devops@intuitivetech.com
License: UNKNOWN
Keywords: aws,saltstack
Platform: UNKNOWN
Classifier: Development Status :: 4 - Beta
Classifier: Intended Audience :: Developers
Classifier: License :: OSI Approved :: MIT License
Classifier: Programming Language :: Python
Classifier: Topic :: System :: Software Distribution
Classifier: Topic :: Utilities
Requires-Dist: aws-decorators
Requires-Dist: boto3
Requires-Dist: jmespath
